pipolars/__init__.py
pipolars/_version.py
pipolars/py.typed
pipolars/api/__init__.py
pipolars/api/client.py
pipolars/api/lazy.py
pipolars/api/query.py
pipolars/cache/__init__.py
pipolars/cache/storage.py
pipolars/cache/strategies.py
pipolars/connection/__init__.py
pipolars/connection/af_database.py
pipolars/connection/auth.py
pipolars/connection/sdk.py
pipolars/connection/server.py
pipolars/core/__init__.py
pipolars/core/config.py
pipolars/core/exceptions.py
pipolars/core/types.py
pipolars/extraction/__init__.py
pipolars/extraction/analyses.py
pipolars/extraction/attributes.py
pipolars/extraction/bulk.py
pipolars/extraction/elements.py
pipolars/extraction/events.py
pipolars/extraction/points.py
pipolars/transform/__init__.py
pipolars/transform/converters.py
pipolars/transform/digital_states.py
pipolars/transform/timestamps.py
pipolars-0.1.3.dist-info/METADATA
pipolars-0.1.3.dist-info/WHEEL
pipolars-0.1.3.dist-info/licenses/LICENSE
pipolars-0.1.3.dist-info/RECORD
