Metadata-Version: 2.4
Name: pipolars
Version: 0.1.3
Summary: High-performance PI System data extraction library with Polars DataFrames
Project-URL: Homepage, https://github.com/aserdargun/pipolars
Project-URL: Documentation, https://pipolars.readthedocs.io
Project-URL: Repository, https://github.com/aserdargun/pipolars
Project-URL: Issues, https://github.com/aserdargun/pipolars/issues
Author: PIPolars Contributors
License: MIT
License-File: LICENSE
Keywords: dataframe,industrial-data,osisoft,pi-system,polars,time-series
Classifier: Development Status :: 3 - Alpha
Classifier: Intended Audience :: Developers
Classifier: Intended Audience :: Science/Research
Classifier: License :: OSI Approved :: MIT License
Classifier: Operating System :: Microsoft :: Windows
Classifier: Programming Language :: Python :: 3
Classifier: Programming Language :: Python :: 3.10
Classifier: Programming Language :: Python :: 3.11
Classifier: Programming Language :: Python :: 3.12
Classifier: Topic :: Database
Classifier: Topic :: Scientific/Engineering
Classifier: Typing :: Typed
Requires-Python: >=3.10
Requires-Dist: polars>=1.17.0
Requires-Dist: pyarrow>=18.0.0
Requires-Dist: pydantic-settings>=2.6.0
Requires-Dist: pydantic>=2.10.0
Requires-Dist: pythonnet>=3.0.3
Requires-Dist: tomli>=2.0.0; python_version < '3.11'
Requires-Dist: tzdata>=2024.1
Provides-Extra: dev
Requires-Dist: mypy>=1.13.0; extra == 'dev'
Requires-Dist: pre-commit>=4.0.0; extra == 'dev'
Requires-Dist: pytest-asyncio>=0.24.0; extra == 'dev'
Requires-Dist: pytest-cov>=6.0.0; extra == 'dev'
Requires-Dist: pytest>=8.3.0; extra == 'dev'
Requires-Dist: ruff>=0.8.0; extra == 'dev'
Provides-Extra: docs
Requires-Dist: furo>=2024.1.0; extra == 'docs'
Requires-Dist: sphinx-autobuild>=2024.2.0; extra == 'docs'
Requires-Dist: sphinx-copybutton>=0.5.2; extra == 'docs'
Requires-Dist: sphinx>=7.2.0; extra == 'docs'
